{
  "light": {
    "color": {
      "accent": { "value": "#004590", "type": "color", "description": "プライマリアクセント" },
      "accent-hover": { "value": "#003070", "type": "color", "description": "ホバー時アクセント" },
      "accent-dim": { "value": "#dce8f7", "type": "color", "description": "アクセント薄色背景" },
      "accent-mid": { "value": "#1a6bc0", "type": "color", "description": "アクセント中間色" },
      "accent-glow": { "value": "rgba(0,69,144,0.12)", "type": "color", "description": "アクセントグロウ" },
      "ai-col": { "value": "#3b35a0", "type": "color", "description": "AI機能カラー" },
      "ai-dim": { "value": "#ebebfa", "type": "color", "description": "AI薄色背景" },
      "ai-mid": { "value": "#5c56cc", "type": "color", "description": "AI中間色" },
      "ai-glow": { "value": "rgba(59,53,160,0.1)", "type": "color", "description": "AIグロウ" },
      "vec": { "value": "#0a6657", "type": "color", "description": "ベクトル検索カラー" },
      "vec-dim": { "value": "#d8f0eb", "type": "color", "description": "ベクトル薄色背景" },
      "vec-mid": { "value": "#0f8f78", "type": "color", "description": "ベクトル中間色" },
      "ok": { "value": "#1e6b0f", "type": "color", "description": "成功・完了" },
      "ok-dim": { "value": "#e4f3de", "type": "color", "description": "成功薄色背景" },
      "warn": { "value": "#7a4b00", "type": "color", "description": "警告" },
      "warn-dim": { "value": "#fdf0d8", "type": "color", "description": "警告薄色背景" },
      "err": { "value": "#8b1a1a", "type": "color", "description": "エラー・危険" },
      "err-dim": { "value": "#fdeaea", "type": "color", "description": "エラー薄色背景" },
      "bg-base": { "value": "#eef0f3", "type": "color", "description": "ページ背景" },
      "bg-surface": { "value": "#ffffff", "type": "color", "description": "カード・パネル背景" },
      "bg-raised": { "value": "#f5f6f8", "type": "color", "description": "浮き上がり要素" },
      "bg-sunken": { "value": "#e4e6ea", "type": "color", "description": "沈み込み要素" },
      "bg-hover": { "value": "#e8eef7", "type": "color", "description": "ホバー状態" },
      "bg-active": { "value": "#d4e2f4", "type": "color", "description": "アクティブ状態" },
      "border-faint": { "value": "rgba(0,30,80,0.07)", "type": "color", "description": "微弱な境界線" },
      "border-default": { "value": "rgba(0,30,80,0.13)", "type": "color", "description": "標準境界線" },
      "border-strong": { "value": "rgba(0,30,80,0.22)", "type": "color", "description": "強い境界線" },
      "border-focus": { "value": "#0050AA", "type": "color", "description": "フォーカスリング" },
      "text-hi": { "value": "#0d1520", "type": "color", "description": "高コントラスト（見出し）" },
      "text-md": { "value": "#3a4554", "type": "color", "description": "中コントラスト（本文）" },
      "text-lo": { "value": "#6b7a8d", "type": "color", "description": "低コントラスト（補助）" },
      "tag-surface": { "value": "#e8ebef", "type": "color", "description": "タグ背景" },
      "topbar-bg": { "value": "#1e3050", "type": "color", "description": "トップバー背景" },
      "sidebar-bg": { "value": "#ffffff", "type": "color", "description": "サイドバー背景" }
    },
    "borderRadius": {
      "sm": { "value": "4", "type": "borderRadius", "description": "小要素（ボタン等）" },
      "md": { "value": "6", "type": "borderRadius", "description": "カード等" },
      "lg": { "value": "10", "type": "borderRadius", "description": "モーダル等" },
      "xl": { "value": "14", "type": "borderRadius", "description": "大パネル" }
    },
    "boxShadow": {
      "xs": { "value": [{ "x": 0, "y": 1, "blur": 2, "spread": 0, "color": "rgba(0,20,60,0.06)", "type": "dropShadow" }], "type": "boxShadow", "description": "ボタン・バッジ" },
      "sm": { "value": [{ "x": 0, "y": 2, "blur": 6, "spread": 0, "color": "rgba(0,20,60,0.08)", "type": "dropShadow" }], "type": "boxShadow", "description": "カード・ドロップダウン" },
      "md": { "value": [{ "x": 0, "y": 4, "blur": 16, "spread": 0, "color": "rgba(0,20,60,0.10)", "type": "dropShadow" }], "type": "boxShadow", "description": "モーダル" },
      "lg": { "value": [{ "x": 0, "y": 8, "blur": 36, "spread": 0, "color": "rgba(0,20,60,0.13)", "type": "dropShadow" }], "type": "boxShadow", "description": "フローティングパネル" }
    },
    "spacing": {
      "0.5": { "value": "2", "type": "spacing" },
      "1": { "value": "4", "type": "spacing" },
      "1.5": { "value": "6", "type": "spacing" },
      "2": { "value": "8", "type": "spacing" },
      "2.5": { "value": "10", "type": "spacing" },
      "3": { "value": "12", "type": "spacing" },
      "4": { "value": "16", "type": "spacing" },
      "5": { "value": "20", "type": "spacing" },
      "6": { "value": "24", "type": "spacing" },
      "8": { "value": "32", "type": "spacing" },
      "10": { "value": "40", "type": "spacing" },
      "12": { "value": "48", "type": "spacing" }
    },
    "fontFamilies": {
      "ui": { "value": "-apple-system, BlinkMacSystemFont, 'Hiragino Sans', 'Yu Gothic UI', 'Meiryo', Arial, sans-serif", "type": "fontFamilies", "description": "UIテキスト用" },
      "mono": { "value": "'SFMono-Regular', Consolas, 'Courier New', monospace", "type": "fontFamilies", "description": "等幅フォント" }
    },
    "fontSize": {
      "badge": { "value": "12", "type": "fontSizes", "description": "バッジ・補助ラベル（最小）" },
      "nav": { "value": "12", "type": "fontSizes", "description": "ナビ・フォームラベル・タグ" },
      "body": { "value": "13", "type": "fontSizes", "description": "本文・入力フィールド" },
      "base": { "value": "14", "type": "fontSizes", "description": "ベースフォントサイズ (1rem)" },
      "subhead": { "value": "15", "type": "fontSizes", "description": "モーダル見出し" },
      "h3": { "value": "16", "type": "fontSizes", "description": "Markdown h1" },
      "h2": { "value": "17", "type": "fontSizes", "description": "ページ見出し" },
      "h1": { "value": "19", "type": "fontSizes", "description": "ダッシュボード大見出し" }
    },
    "typography": {
      "heading-h1": {
        "value": { "fontFamily": "{fontFamilies.ui}", "fontWeight": "Bold", "fontSize": "{fontSize.h1}", "lineHeight": "1.4" },
        "type": "typography",
        "description": "ダッシュボード大見出し 19px"
      },
      "heading-h2": {
        "value": { "fontFamily": "{fontFamilies.ui}", "fontWeight": "Bold", "fontSize": "{fontSize.h2}", "lineHeight": "1.4" },
        "type": "typography",
        "description": "ページ見出し 17px"
      },
      "heading-h3": {
        "value": { "fontFamily": "{fontFamilies.ui}", "fontWeight": "Bold", "fontSize": "{fontSize.h3}", "lineHeight": "1.4" },
        "type": "typography",
        "description": "セクション見出し 16px"
      },
      "heading-subhead": {
        "value": { "fontFamily": "{fontFamilies.ui}", "fontWeight": "Semi Bold", "fontSize": "{fontSize.subhead}", "lineHeight": "1.4" },
        "type": "typography",
        "description": "モーダル見出し 15px"
      },
      "body-base": {
        "value": { "fontFamily": "{fontFamilies.ui}", "fontWeight": "Regular", "fontSize": "{fontSize.base}", "lineHeight": "1.6" },
        "type": "typography",
        "description": "ベースフォント 14px"
      },
      "body-default": {
        "value": { "fontFamily": "{fontFamilies.ui}", "fontWeight": "Regular", "fontSize": "{fontSize.body}", "lineHeight": "1.6" },
        "type": "typography",
        "description": "本文 13px"
      },
      "label-nav": {
        "value": { "fontFamily": "{fontFamilies.ui}", "fontWeight": "Medium", "fontSize": "{fontSize.nav}", "lineHeight": "1.4" },
        "type": "typography",
        "description": "ナビ・ラベル 12px"
      },
      "label-badge": {
        "value": { "fontFamily": "{fontFamilies.ui}", "fontWeight": "Semi Bold", "fontSize": "{fontSize.badge}", "lineHeight": "1.2" },
        "type": "typography",
        "description": "バッジ 12px"
      },
      "mono-code": {
        "value": { "fontFamily": "{fontFamilies.mono}", "fontWeight": "Regular", "fontSize": "{fontSize.body}", "lineHeight": "1.5" },
        "type": "typography",
        "description": "コード・数値 13px等幅"
      }
    }
  },
  "dark": {
    "color": {
      "accent": { "value": "#5a9ae0", "type": "color" },
      "accent-hover": { "value": "#78b0ec", "type": "color" },
      "accent-dim": { "value": "#0e1e36", "type": "color" },
      "accent-mid": { "value": "#5a9ae0", "type": "color" },
      "accent-glow": { "value": "rgba(90,154,224,0.18)", "type": "color" },
      "ai-col": { "value": "#9a92f0", "type": "color" },
      "ai-dim": { "value": "#1a1830", "type": "color" },
      "ai-mid": { "value": "#9a92f0", "type": "color" },
      "ai-glow": { "value": "rgba(154,146,240,0.14)", "type": "color" },
      "vec": { "value": "#38d0b0", "type": "color" },
      "vec-dim": { "value": "#082420", "type": "color" },
      "vec-mid": { "value": "#38d0b0", "type": "color" },
      "ok": { "value": "#6cc850", "type": "color" },
      "ok-dim": { "value": "#0e1f08", "type": "color" },
      "warn": { "value": "#f0b040", "type": "color" },
      "warn-dim": { "value": "#201600", "type": "color" },
      "err": { "value": "#f06060", "type": "color" },
      "err-dim": { "value": "#200808", "type": "color" },
      "bg-base": { "value": "#10141c", "type": "color" },
      "bg-surface": { "value": "#181d28", "type": "color" },
      "bg-raised": { "value": "#1f2535", "type": "color" },
      "bg-sunken": { "value": "#0c1018", "type": "color" },
      "bg-hover": { "value": "#232c3e", "type": "color" },
      "bg-active": { "value": "#1a2d4a", "type": "color" },
      "border-faint": { "value": "rgba(160,185,230,0.10)", "type": "color" },
      "border-default": { "value": "rgba(160,185,230,0.18)", "type": "color" },
      "border-strong": { "value": "rgba(160,185,230,0.28)", "type": "color" },
      "border-focus": { "value": "#5a9eff", "type": "color" },
      "text-hi": { "value": "#e8f0ff", "type": "color" },
      "text-md": { "value": "#a8bcd8", "type": "color" },
      "text-lo": { "value": "#6e84a0", "type": "color" },
      "tag-surface": { "value": "#1f2535", "type": "color" },
      "topbar-bg": { "value": "#0c1018", "type": "color" },
      "sidebar-bg": { "value": "#181d28", "type": "color" }
    },
    "boxShadow": {
      "xs": { "value": [{ "x": 0, "y": 1, "blur": 3, "spread": 0, "color": "rgba(0,0,0,0.35)", "type": "dropShadow" }], "type": "boxShadow" },
      "sm": { "value": [{ "x": 0, "y": 2, "blur": 8, "spread": 0, "color": "rgba(0,0,0,0.4)", "type": "dropShadow" }], "type": "boxShadow" },
      "md": { "value": [{ "x": 0, "y": 4, "blur": 20, "spread": 0, "color": "rgba(0,0,0,0.5)", "type": "dropShadow" }], "type": "boxShadow" },
      "lg": { "value": [{ "x": 0, "y": 8, "blur": 40, "spread": 0, "color": "rgba(0,0,0,0.6)", "type": "dropShadow" }], "type": "boxShadow" }
    }
  },
  "eng": {
    "color": {
      "accent": { "value": "#00c896", "type": "color" },
      "accent-hover": { "value": "#00e0aa", "type": "color" },
      "accent-dim": { "value": "rgba(0,200,150,0.1)", "type": "color" },
      "accent-mid": { "value": "#00c896", "type": "color" },
      "accent-glow": { "value": "rgba(0,200,150,0.2)", "type": "color" },
      "ai-col": { "value": "#60a8e8", "type": "color" },
      "ai-dim": { "value": "rgba(96,168,232,0.1)", "type": "color" },
      "ai-mid": { "value": "#60a8e8", "type": "color" },
      "ai-glow": { "value": "rgba(96,168,232,0.15)", "type": "color" },
      "vec": { "value": "#a0e060", "type": "color" },
      "vec-dim": { "value": "rgba(160,224,96,0.08)", "type": "color" },
      "vec-mid": { "value": "#a0e060", "type": "color" },
      "ok": { "value": "#5cc840", "type": "color" },
      "ok-dim": { "value": "rgba(92,200,64,0.1)", "type": "color" },
      "warn": { "value": "#e8b040", "type": "color" },
      "warn-dim": { "value": "rgba(232,176,64,0.1)", "type": "color" },
      "err": { "value": "#f05050", "type": "color" },
      "err-dim": { "value": "rgba(240,80,80,0.1)", "type": "color" },
      "bg-base": { "value": "#1a1f26", "type": "color" },
      "bg-surface": { "value": "#222830", "type": "color" },
      "bg-raised": { "value": "#2a3040", "type": "color" },
      "bg-sunken": { "value": "#141820", "type": "color" },
      "bg-hover": { "value": "#2e3848", "type": "color" },
      "bg-active": { "value": "#1a2e48", "type": "color" },
      "border-faint": { "value": "rgba(100,160,220,0.10)", "type": "color" },
      "border-default": { "value": "rgba(100,160,220,0.20)", "type": "color" },
      "border-strong": { "value": "rgba(100,160,220,0.32)", "type": "color" },
      "border-focus": { "value": "#00c896", "type": "color" },
      "text-hi": { "value": "#d8eaf8", "type": "color" },
      "text-md": { "value": "#92b0cc", "type": "color" },
      "text-lo": { "value": "#5e7890", "type": "color" },
      "tag-surface": { "value": "rgba(100,160,220,0.08)", "type": "color" },
      "topbar-bg": { "value": "#141820", "type": "color" },
      "sidebar-bg": { "value": "#1a1f26", "type": "color" }
    },
    "borderRadius": {
      "sm": { "value": "3", "type": "borderRadius" },
      "md": { "value": "5", "type": "borderRadius" },
      "lg": { "value": "8", "type": "borderRadius" },
      "xl": { "value": "12", "type": "borderRadius" }
    },
    "fontFamilies": {
      "ui": { "value": "'SF Mono', Consolas, 'Courier New', monospace", "type": "fontFamilies", "description": "Engineering: UI/monoとも等幅" },
      "mono": { "value": "'SF Mono', Consolas, 'Courier New', monospace", "type": "fontFamilies" }
    },
    "boxShadow": {
      "xs": { "value": [{ "x": 0, "y": 1, "blur": 3, "spread": 0, "color": "rgba(0,0,0,0.5)", "type": "dropShadow" }], "type": "boxShadow" },
      "sm": { "value": [{ "x": 0, "y": 2, "blur": 8, "spread": 0, "color": "rgba(0,0,0,0.55)", "type": "dropShadow" }, { "x": 0, "y": 0, "blur": 6, "spread": 0, "color": "rgba(0,200,150,0.04)", "type": "dropShadow" }], "type": "boxShadow" },
      "md": { "value": [{ "x": 0, "y": 4, "blur": 20, "spread": 0, "color": "rgba(0,0,0,0.6)", "type": "dropShadow" }, { "x": 0, "y": 0, "blur": 16, "spread": 0, "color": "rgba(0,200,150,0.06)", "type": "dropShadow" }], "type": "boxShadow" },
      "lg": { "value": [{ "x": 0, "y": 8, "blur": 40, "spread": 0, "color": "rgba(0,0,0,0.7)", "type": "dropShadow" }, { "x": 0, "y": 0, "blur": 32, "spread": 0, "color": "rgba(0,200,150,0.08)", "type": "dropShadow" }], "type": "boxShadow" }
    }
  },
  "cae": {
    "color": {
      "accent": { "value": "#e89020", "type": "color" },
      "accent-hover": { "value": "#f0a838", "type": "color" },
      "accent-dim": { "value": "rgba(232,144,32,0.1)", "type": "color" },
      "accent-mid": { "value": "#e89020", "type": "color" },
      "accent-glow": { "value": "rgba(232,144,32,0.2)", "type": "color" },
      "ai-col": { "value": "#60c8f0", "type": "color" },
      "ai-dim": { "value": "rgba(96,200,240,0.08)", "type": "color" },
      "ai-mid": { "value": "#60c8f0", "type": "color" },
      "ai-glow": { "value": "rgba(96,200,240,0.15)", "type": "color" },
      "vec": { "value": "#30d8c0", "type": "color" },
      "vec-dim": { "value": "rgba(48,216,192,0.08)", "type": "color" },
      "vec-mid": { "value": "#30d8c0", "type": "color" },
      "ok": { "value": "#60c840", "type": "color" },
      "ok-dim": { "value": "rgba(96,200,64,0.1)", "type": "color" },
      "warn": { "value": "#f0a030", "type": "color" },
      "warn-dim": { "value": "rgba(240,160,48,0.1)", "type": "color" },
      "err": { "value": "#f05840", "type": "color" },
      "err-dim": { "value": "rgba(240,88,64,0.1)", "type": "color" },
      "bg-base": { "value": "#0e1014", "type": "color" },
      "bg-surface": { "value": "#14181e", "type": "color" },
      "bg-raised": { "value": "#1c2028", "type": "color" },
      "bg-sunken": { "value": "#0a0c10", "type": "color" },
      "bg-hover": { "value": "#1e2430", "type": "color" },
      "bg-active": { "value": "#142030", "type": "color" },
      "border-faint": { "value": "rgba(220,180,80,0.10)", "type": "color" },
      "border-default": { "value": "rgba(220,180,80,0.20)", "type": "color" },
      "border-strong": { "value": "rgba(220,180,80,0.30)", "type": "color" },
      "border-focus": { "value": "#e89020", "type": "color" },
      "text-hi": { "value": "#f0ece4", "type": "color" },
      "text-md": { "value": "#b8a898", "type": "color" },
      "text-lo": { "value": "#6e6058", "type": "color" },
      "tag-surface": { "value": "rgba(220,180,80,0.07)", "type": "color" },
      "topbar-bg": { "value": "#0a0c10", "type": "color" },
      "sidebar-bg": { "value": "#0e1014", "type": "color" }
    },
    "borderRadius": {
      "sm": { "value": "2", "type": "borderRadius" },
      "md": { "value": "4", "type": "borderRadius" },
      "lg": { "value": "6", "type": "borderRadius" },
      "xl": { "value": "10", "type": "borderRadius" }
    },
    "fontFamilies": {
      "ui": { "value": "'SF Mono', Consolas, 'Courier New', monospace", "type": "fontFamilies", "description": "CAE: UI/monoとも等幅" },
      "mono": { "value": "'SF Mono', Consolas, 'Courier New', monospace", "type": "fontFamilies" }
    },
    "boxShadow": {
      "xs": { "value": [{ "x": 0, "y": 1, "blur": 3, "spread": 0, "color": "rgba(0,0,0,0.6)", "type": "dropShadow" }], "type": "boxShadow" },
      "sm": { "value": [{ "x": 0, "y": 2, "blur": 8, "spread": 0, "color": "rgba(0,0,0,0.65)", "type": "dropShadow" }, { "x": 0, "y": 0, "blur": 8, "spread": 0, "color": "rgba(232,144,32,0.05)", "type": "dropShadow" }], "type": "boxShadow" },
      "md": { "value": [{ "x": 0, "y": 4, "blur": 20, "spread": 0, "color": "rgba(0,0,0,0.75)", "type": "dropShadow" }, { "x": 0, "y": 0, "blur": 20, "spread": 0, "color": "rgba(232,144,32,0.07)", "type": "dropShadow" }], "type": "boxShadow" },
      "lg": { "value": [{ "x": 0, "y": 8, "blur": 40, "spread": 0, "color": "rgba(0,0,0,0.85)", "type": "dropShadow" }, { "x": 0, "y": 0, "blur": 40, "spread": 0, "color": "rgba(232,144,32,0.1)", "type": "dropShadow" }], "type": "boxShadow" }
    }
  },
  "$themes": [
    { "id": "light", "name": "Light", "selectedTokenSets": { "light": "enabled" }, "group": "Theme" },
    { "id": "dark", "name": "Dark", "selectedTokenSets": { "dark": "enabled", "light": "source" }, "group": "Theme" },
    { "id": "eng", "name": "Engineering", "selectedTokenSets": { "eng": "enabled", "light": "source" }, "group": "Theme" },
    { "id": "cae", "name": "CAE", "selectedTokenSets": { "cae": "enabled", "light": "source" }, "group": "Theme" }
  ],
  "$metadata": {
    "tokenSetOrder": ["light", "dark", "eng", "cae"]
  }
}
